autoprofile_client/__init__.py
autoprofile_client/client.py
autoprofile_client-0.0.4.dist-info/LICENSE
autoprofile_client-0.0.4.dist-info/METADATA
autoprofile_client-0.0.4.dist-info/WHEEL
autoprofile_client-0.0.4.dist-info/top_level.txt
autoprofile_client-0.0.4.dist-info/RECORD
