Metadata-Version: 2.2
Name: autoprofile_client
Version: 0.0.4
Summary: Client package for autoprofiling
Author-email: Yi Kuo <kuokuoyiyi@gmail.com>
License: MIT License
Classifier: Programming Language :: Python :: 3
Classifier: Operating System :: OS Independent
Requires-Python: >=3.5
License-File: LICENSE
